<?xml version='1.0' encoding='UTF-8'?>
<root>
  <discipline>Линейная алгебра и функция нескольких переменных</discipline>
  <profile>Веб-технологии</profile>
  <course>#TODO</course>
  <status>В разработке</status>
  <elective>#TODO</elective>
  <files>
    <rpd>#TODO</rpd>
    <annotation>#TODO</annotation>
    <fos>#TODO</fos>
    <method>#TODO</method>
    <review>#TODO</review>
    <plan>#TODO</plan>
    <matrix>#TODO</matrix>
    <program>#TODO</program>
  </files>
  <targets>
    <target></target>
  </targets>
  <tasks>
    <task></task>
  </tasks>
  <sections/>
  <disciplines/>
  <sections_content/>
  <marks>
    <competency>#TODO</competency>
    <attestation>#TODO</attestation>
    <brs>#TODO</brs>
    <brs_description>#TODO</brs_description>
    <competencies/>
    <intermediate/>
  </marks>
  <literature>
    <main/>
    <additional/>
    <digital/>
  </literature>
  <software>
    <program>#TODO</program>
  </software>
  <evaluation_tools>
    <tool>#TODO</tool>
  </evaluation_tools>
  <tasks>
    <task>#TODO</task>
  </tasks>
</root>
